src/pre_processing/absolute_value.vhd
library IEEE; 
use IEEE.STD_LOGIC_1164.ALL;
use IEEE.NUMERIC_STD.ALL;

entity absolute_value is
    Port ( clk       : in  STD_LOGIC;
           rst       : in  STD_LOGIC;
           valid_in  : in  STD_LOGIC;
           x_in      : in  signed(15 downto 0);   
           valid_out : out STD_LOGIC;
           y_out     : out signed(15 downto 0)   
         );
end absolute_value;

architecture Behavioral of absolute_value is
    signal y_out_int : signed(15 downto 0); 
begin
    process(clk, rst)
    begin
        if rst = '1' then
            y_out_int <= (others => '0');
            valid_out <= '0';
        elsif rising_edge(clk) then
            if valid_in = '1' then
                if x_in(15) = '1' then 
                    y_out_int <= -x_in; 
                else
                    y_out_int <= x_in;  
                end if;
                valid_out <= '1';
            else
                valid_out <= '0';
            end if;
        end if;
    end process;                    
    y_out <= y_out_int;
end Behavioral;

src/pre_processing/type_4_bandpass_filter.vhd
library IEEE;
use IEEE.STD_LOGIC_1164.ALL;
use IEEE.NUMERIC_STD.ALL;

-- Package for array types
package filter_types is
    type x_array_type is array(0 to 4) of signed(15 downto 0);
    type y_array_type is array(1 to 4) of signed(15 downto 0);
end package;

library IEEE;
use IEEE.STD_LOGIC_1164.ALL;
use IEEE.NUMERIC_STD.ALL;
use work.filter_types.all;

entity type_4_bandpass_filter is
    Port (
        clk       : in  STD_LOGIC;
        rst       : in  STD_LOGIC;
        valid_in  : in  STD_LOGIC;
        x_in      : in  signed(15 downto 0);     -- Q1.15 input
        valid_out : out STD_LOGIC;
        y_out     : out signed(15 downto 0);     -- Q1.15 output (extended to 32 bits)

        -- Debug ports
        acc_out                 : out signed(55 downto 0);
        x_0, x_1, x_2, x_3, x_4 : out signed(15 downto 0);
        y_1, y_2, y_3, y_4      : out signed(15 downto 0);
        a1_mult_result          : out signed(47 downto 0)
    );
end type_4_bandpass_filter;

architecture Behavioral of type_4_bandpass_filter is

    -- Coefficients in Q2.30 fixed-point
    constant b0 : signed(31 downto 0) := to_signed(625451352, 32);
    constant b1 : signed(31 downto 0) := to_signed(0, 32);
    constant b2 : signed(31 downto 0) := to_signed(-1251168932, 32);
    constant b3 : signed(31 downto 0) := to_signed(0, 32);
    constant b4 : signed(31 downto 0) := to_signed(625451352, 32);

    constant a1 : signed(31 downto 0) := to_signed(-737915354, 32);
    constant a2 : signed(31 downto 0) := to_signed(-875560496, 32);
    constant a3 : signed(31 downto 0) := to_signed(208097889, 32);
    constant a4 : signed(31 downto 0) := to_signed(373198311, 32);

    -- Delay registers
    signal x_reg : x_array_type;
    signal y_reg : y_array_type;

    signal y_out_int : signed(15 downto 0);
    signal acc_out_int : signed(55 downto 0);
    signal a1_mult_result_int : signed(47 downto 0);

begin

    process(clk, rst)
        variable acc  : signed(55 downto 0);  -- wide accumulator
        variable mult : signed(47 downto 0);  -- 16x32 multiplication
    begin
        if rst = '1' then
            x_reg       <= (others => (others => '0'));
            y_reg       <= (others => (others => '0'));
            y_out_int   <= (others => '0');
            acc_out_int <= (others => '0');
            a1_mult_result_int <= (others => '0');
            valid_out   <= '0';
            
        elsif rising_edge(clk) then
            if valid_in = '1' then
                -- Reset accumulator
                acc := (others => '0');

                -- Feedforward (b coefficients * inputs)
                mult := b0 * x_in;
                acc := acc + resize(mult, 56);
                
                mult := b1 * x_reg(0);
                acc := acc + resize(mult, 56);

                mult := b2 * x_reg(1);
                acc := acc + resize(mult, 56);

                mult := b3 * x_reg(2);
                acc := acc + resize(mult, 56);

                mult := b4 * x_reg(3);
                acc := acc + resize(mult, 56);

                -- Feedback (a coefficients * outputs)
                mult := a1 * y_reg(1);
                a1_mult_result_int <= mult;
                acc := acc - resize(mult, 56);

                mult := a2 * y_reg(2);
                acc := acc - resize(mult, 56);

                mult := a3 * y_reg(3);
                acc := acc - resize(mult, 56);

                mult := a4 * y_reg(4);
                acc := acc - resize(mult, 56);

                acc_out_int <= acc;

                -- Normalize back to Q1.15 (shift right by 30)
                y_out_int <= resize(shift_right(acc, 30), 16);

                -- Update delay lines
                x_reg(1 to 4) <= x_reg(0 to 3);
                x_reg(0)      <= x_in;

                y_reg(2 to 4) <= y_reg(1 to 3);
                y_reg(1)      <= resize(shift_right(acc, 30), 16);

                valid_out <= '1';
            else
                valid_out <= '0';
            end if;
        end if;
    end process;

    -- Debug assignments
    x_0 <= x_reg(0);
    x_1 <= x_reg(1);
    x_2 <= x_reg(2);
    x_3 <= x_reg(3);
    x_4 <= x_reg(4);

    y_1 <= y_reg(1);
    y_2 <= y_reg(2);
    y_3 <= y_reg(3);
    y_4 <= y_reg(4);

    y_out <= y_out_int;

    acc_out <= acc_out_int;

    a1_mult_result <= a1_mult_result_int;

end Behavioral;

src/pre_processing/tests/bandpass_absolute/bandpass_abs.vhd
library IEEE;
use IEEE.STD_LOGIC_1164.ALL;
use IEEE.NUMERIC_STD.ALL;

entity bandpass_abs is
    Port ( clk        : in  STD_LOGIC;
           rst        : in  STD_LOGIC;
           valid_in   : in  STD_LOGIC;
           x_in       : in  signed(15 downto 0);
           y_out      : out signed(15 downto 0);
           valid_out  : out STD_LOGIC
         );
end bandpass_abs;


architecture rtl of bandpass_abs is
    signal bp_y_out    : signed(15 downto 0);
    signal abs_y_out   : signed(15 downto 0);   
    -- signal lp_y_out    : signed(15 downto 0);
    -- signal ma_y_out    : signed(15 downto 0);
    signal valid_bp    : std_logic;
    signal valid_abs   : std_logic;
    -- signal valid_lp    : std_logic;
    -- signal valid_ma    : std_logic;

    begin 
        bp_instance: entity work.type_4_bandpass_filter
            port map (
                clk       => clk,
                rst       => rst,
                valid_in  => '1',
                x_in      => x_in,
                valid_out => valid_bp,
                y_out     => bp_y_out
            );
        abs_instance: entity work.absolute_value
            port map (
                clk       => clk,
                rst       => rst,
                valid_in  => valid_bp,
                x_in      => bp_y_out,
                valid_out => valid_abs,
                y_out     => abs_y_out
            );

        -- ma_instance: entity work.moving_average_filter
        --     port map (
        --         clk       => clk,
        --         rst       => rst,
        --         valid_in  => valid_abs,
        --         x_in      => abs_y_out,
        --         valid_out => valid_ma,
        --         y_out     => ma_y_out
        --         -- sum_debug => open  -- Optional debug output, not used
        --     );

        -- lp_instance: entity work.type_1_lowpass_filter
        --     port map (
        --         clk       => clk,
        --         rst       => rst,
        --         valid_in  => valid_ma,
        --         x_in      => ma_y_out,
        --         valid_out => valid_lp,
        --         y_out     => lp_y_out
        --     );
        y_out     <= abs_y_out;
        valid_out <= valid_abs;
end rtl;

src/pre_processing/tests/bandpass_absolute/tb_bandpass_abs.vhd
library IEEE; 
use IEEE.STD_LOGIC_1164.ALL;
use IEEE.NUMERIC_STD.ALL;
use std.textio.ALL;
use work.filter_types.all;

entity tb_bandpass_abs is
end tb_bandpass_abs;

architecture Behavioral of tb_bandpass_abs is
    -- Testbench signals
    signal clk       : std_logic := '0';
    signal rst       : std_logic := '0';
    signal x_in      : signed(15 downto 0) := (others => '0');
    signal y_out     : signed(15 downto 0);
    signal valid_in  : std_logic := '0';
    signal valid_out : std_logic;

    constant clk_period : time := 10 ns;
    constant sim_time   : time := 1000000 ns;

begin 
    -- Instantiate the DUT
    uut: entity work.bandpass_abs
        port map (
            clk    => clk,
            rst    => rst,
            valid_in  => valid_in,
            x_in   => x_in,
            valid_out => valid_out,
            y_out  => y_out
        );

    -- Clock generation
    clk_process : process
    begin
        while now < sim_time loop
            clk <= '0';
            wait for clk_period/2;
            clk <= '1';
            wait for clk_period/2;
        end loop;
        wait;
    end process;

    stim_proc: process
        file infile : text open read_mode is "ppg.txt";
        file outfile : text open write_mode is "filter_output.txt";
        variable L : line;
        -- variable time_val, ppg_val, ecg_val, resp_val : real;
        variable ppg_val : real;
        variable out_val : real;
        -- variable header_line : line;
        variable out_line : line;
    begin
        -- Reset
        rst <= '1';
        wait for 2*clk_period;
        rst <= '0';
        wait for clk_period;

        -- Skip header line if file is not empty
        -- if not endfile(infile) then
        --     readline(infile, header_line); -- Read and ignore header line
        -- end if;

        -- Read data from CSV file
        while not endfile(infile) loop
            readline(infile, L);
            -- read(L, time_val);
            read(L, ppg_val);
            report "Read PPG: " & real'image(ppg_val);
            -- read(L, ecg_val);
            -- read(L, resp_val);

            -- Apply PPG value to filter input (scaled to Q1.15)
            x_in <= to_signed(integer(ppg_val * 32767.0), 16);
            valid_in <= '1';
            
            wait until rising_edge(clk);
            
            -- Write output if valid
            if valid_out = '1' then
                -- out_val := real(to_integer(y_out)) / 32768.0; -- Convert back from Q1.15
                out_val := real(to_integer(y_out)); -- Convert back from Q1.15
                write(out_line, ppg_val);
                write(out_line, string'(","));
                write(out_line, out_val);
                writeline(outfile, out_line);
            end if;
            
            valid_in <= '0';
            wait for clk_period;
        end loop;
        
        wait for 10*clk_period;
        report "End of simulation";
        wait;
    end process;

end Behavioral;

src/pre_processing/tests/bandpass_absolute/bandpass_abs.vcd
$date
  Wed Oct  8 20:36:43 2025
$end
$version
  GHDL v0
$end
$timescale
  1 fs
$end
$scope module standard $end
$upscope $end
$scope module std_logic_1164 $end
$upscope $end
$scope module numeric_std $end
$upscope $end
$scope module textio $end
$upscope $end
$scope module filter_types $end
$upscope $end
$scope module tb_bandpass_abs $end
$var reg 1 ! clk $end
$var reg 1 " rst $end
$var reg 16 # x_in[15:0] $end
$var reg 16 $ y_out[15:0] $end
$var reg 1 % valid_in $end
$var reg 1 & valid_out $end
$scope module uut $end
$var reg 1 ' clk $end
$var reg 1 ( rst $end
$var reg 1 ) valid_in $end
$var reg 16 * x_in[15:0] $end
$var reg 16 + y_out[15:0] $end
$var reg 1 , valid_out $end
$var reg 16 - bp_y_out[15:0] $end
$var reg 16 . abs_y_out[15:0] $end
$var reg 1 / valid_bp $end
$var reg 1 0 valid_abs $end
$scope module bp_instance $end
$var reg 1 1 clk $end
$var reg 1 2 rst $end
$var reg 1 3 valid_in $end
$var reg 16 4 x_in[15:0] $end
$var reg 1 5 valid_out $end
$var reg 16 6 y_out[15:0] $end
$comment x_reg is not handled $end
$comment y_reg is not handled $end
$var reg 16 7 y_out_int[15:0] $end
$var reg 56 8 acc_out_int[55:0] $end
$var reg 48 9 a1_mult_result_int[47:0] $end
$upscope $end
$scope module abs_instance $end
$var reg 1 : clk $end
$var reg 1 ; rst $end
$var reg 1 < valid_in $end
$var reg 16 = x_in[15:0] $end
$var reg 1 > valid_out $end
$var reg 16 ? y_out[15:0] $end
$var reg 16 @ y_out_int[15:0] $end
$upscope $end
$upscope $end
$upscope $end
$enddefinitions $end
#0
0!
1"
b0000000000000000 #
b0000000000000000 $
0%
0&
0'
1(
0)
b0000000000000000 *
b0000000000000000 +
0,
b0000000000000000 -
b0000000000000000 .
0/
00
01
12
13
b0000000000000000 4
05
b0000000000000000 6
b0000000000000000 7
b00000000000000000000000000000000000000000000000000000000 8
b000000000000000000000000000000000000000000000000 9
0:
1;
0<
b0000000000000000 =
0>
b0000000000000000 ?
b0000000000000000 @
#5000000
1!
1'
11
1:
#10000000
0!
0'
01
0:
#15000000
1!
1'
11
1:
#20000000
0!
0"
0'
0(
01
02
0:
0;
#25000000
1!
1'
1/
11
15
1:
1<
#30000000
0!
b0011010010001101 #
1%
0'
1)
b0011010010001101 *
01
b0011010010001101 4
0:
#35000000
1!
0%
1&
1'
0)
1,
b0001111010011100 -
10
11
b0001111010011100 6
b0001111010011100 7
b00000000000001111010011100010101001110011011110101111000 8
1:
b0001111010011100 =
1>
#40000000
0!
0'
01
0:
#45000000
1!
b0011001101001100 #
b0001111010011100 $
0%
1'
0)
b0011001101001100 *
b0001111010011100 +
b0011001011101010 -
b0001111010011100 .
11
b0011001101001100 4
b0011001011101010 6
b0011001011101010 7
b00000000000011001011101010100010101000000101101011111000 8
b111110101011110110110011110010000001001100101000 9
1:
b0011001011101010 =
b0001111010011100 ?
b0001111010011100 @
#50000000
0!
0'
01
0:
#55000000
1!
b0011001000001100 #
b0011001011101010 $
0%
1'
0)
b0011001000001100 *
b0011001011101010 +
b0001101111011110 -
b0011001011101010 .
11
b0011001000001100 4
b0001101111011110 6
b0001101111011110 7
b00000000000001101111011110000110110001101001011001010000 8
b111101110100000010100011001100101101101010111100 9
1:
b0001101111011110 =
b0011001011101010 ?
b0011001011101010 @
#60000000
0!
0'
01
0:
#65000000
1!
b0011000011101100 #
b0001101111011110 $
0%
1'
0)
b0011000011101100 *
b0001101111011110 +
b0001011101110101 -
b0001101111011110 .
11
b0011000011101100 4
b0001011101110101 6
b0001011101110101 7
b00000000000001011101110101101000000000100110100001000000 8
b111110110011011001001111111110011100011011110100 9
1:
b0001011101110101 =
b0001101111011110 ?
b0001101111011110 @
#70000000
0!
0'
01
0:
#75000000
1!
b0010111110101100 #
b0001011101110101 $
0%
1'
0)
b0010111110101100 *
b0001011101110101 +
b0001001001100110 -
b0001011101110101 .
11
b0010111110101100 4
b0001001001100110 6
b0001001001100110 7
b00000000000001001001100110100100000101011111011110111100 8
b111110111111100001001000111111010010000101011110 9
1:
b0001001001100110 =
b0001011101110101 ?
b0001011101110101 @
#80000000
0!
0'
01
0:
#85000000
1!
b0010111010001011 #
b0001001001100110 $
0%
1'
0)
b0010111010001011 *
b0001001001100110 +
b0000100010101001 -
b0001001001100110 .
11
b0010111010001011 4
b0000100010101001 6
b0000100010101001 7
b00000000000000100010101001000010010111010001100001000000 8
b111111001101011011000111001101011100111100100100 9
1:
b0000100010101001 =
b0001001001100110 ?
b0001001001100110 @
#90000000
0!
0'
01
0:
#95000000
1!
b0010110110001011 #
b0000100010101001 $
0%
1'
0)
b0010110110001011 *
b0000100010101001 +
b0000011011011010 -
b0000100010101001 .
11
b0010110110001011 4
b0000011011011010 6
b0000011011011010 7
b00000000000000011011011010100101110110000100100000011011 8
b111111101000001100011001010010001100011100010110 9
1:
b0000011011011010 =
b0000100010101001 ?
b0000100010101001 @
#100000000
0!
0'
01
0:
#105000000
1!
b0010110010101011 #
b0000011011011010 $
0%
1'
0)
b0010110010101011 *
b0000011011011010 +
b0000000001010101 -
b0000011011011010 .
11
b0010110010101011 4
b0000000001010101 6
b0000000001010101 7
b00000000000000000001010101011011110110100110100011110111 8
b111111101101001010100101011111110111000001011100 9
1:
b0000000001010101 =
b0000011011011010 ?
b0000011011011010 @
#110000000
0!
0'
01
0:
#115000000
1!
b0010110000001011 #
b0000000001010101 $
0%
1'
0)
b0010110000001011 *
b0000000001010101 +
b1111111000011000 -
b0000000001010101 .
11
b0010110000001011 4
b1111111000011000 6
b1111111000011000 7
b11111111111111111000011000110110110000000101101100001011 8
b111111111111000101100101011011011111001010011110 9
1:
b1111111000011000 =
b0000000001010101 ?
b0000000001010101 @
#120000000
0!
0'
01
0:
#125000000
1!
b0010101101101011 #
b0000000111101000 $
0%
1'
0)
b0010101101101011 *
b0000000111101000 +
b1111101011111001 -
b0000000111101000 .
11
b0010101101101011 4
b1111101011111001 6
b1111101011111001 7
b11111111111111101011111001110011110011110100101101001011 8
b000000000101001111010111110010110000011110010000 9
1:
b1111101011111001 =
b0000000111101000 ?
b0000000111101000 @
#130000000
0!
0'
01
0:
#135000000
1!
b0010101011101010 #
b0000010100000111 $
0%
1'
0)
b0010101011101010 *
b0000010100000111 +
b1111100011000000 -
b0000010100000111 .
11
b0010101011101010 4
b1111100011000000 6
b1111100011000000 7
b11111111111111100011000000000001111010111111101011001011 8
b000000001101110100011110010110110001111011110110 9
1:
b1111100011000000 =
b0000010100000111 ?
b0000010100000111 @
#140000000
0!
0'
01
0:
#145000000
1!
b0010101001001010 #
b0000011101000000 $
0%
1'
0)
b0010101001001010 *
b0000011101000000 +
b1111011100111011 -
b0000011101000000 .
11
b0010101001001010 4
b1111011100111011 6
b1111011100111011 7
b11111111111111011100111011010111011010110111111000010001 8
b000000010011111011100000110010010110110010000000 9
1:
b1111011100111011 =
b0000011101000000 ?
b0000011101000000 @
#150000000
0!
0'
01
0:
#155000000
1!
b0010100110101010 #
b0000100011000101 $
0%
1'
0)
b0010100110101010 *
b0000100011000101 +
b1111010110011101 -
b0000100011000101 .
11
b0010100110101010 4
b1111010110011101 6
b1111010110011101 7
b11111111111111010110011101111110011110101111011010001101 8
b000000011000000110110110001111101010110011000010 9
1:
b1111010110011101 =
b0000100011000101 ?
b0000100011000101 @
#160000000
0!
0'
01
0:
#165000000
1!
b0010100100001010 #
b0000101001100011 $
0%
1'
0)
b0010100100001010 *
b0000101001100011 +
b1111010011001000 -
b0000101001100011 .
11
b0010100100001010 4
b1111010011001000 6
b1111010011001000 7
b11111111111111010011001000010001111100010000111100100011 8
b000000011100100011010111010010000100101101001110 9
1:
b1111010011001000 =
b0000101001100011 ?
b0000101001100011 @
#170000000
0!
0'
01
0:
#175000000
1!
b0010100010001010 #
b0000101100111000 $
0%
1'
0)
b0010100010001010 *
b0000101100111000 +
b1111010000011010 -
b0000101100111000 .
11
b0010100010001010 4
b1111010000011010 6
b1111010000011010 7
b11111111111111010000011010001101000111010100010000011101 8
b000000011110110101101111101100110100010110110000 9
1:
b1111010000011010 =
b0000101100111000 ?
b0000101100111000 @
#180000000
0!
0'
01
0:
#185000000
1!
b0010011111101010 #
b0000101111100110 $
0%
1'
0)
b0010011111101010 *
b0000101111100110 +
b1111001111001100 -
b0000101111100110 .
11
b0010011111101010 4
b1111001111001100 6
b1111001111001100 7
b11111111111111001111001100011010110010101011010101100010 8
b000000100000101101010100110001100010011111011100 9
1:
b1111001111001100 =
b0000101111100110 ?
b0000101111100110 @
#190000000
0!
0'
01
0:
#195000000
1!
b0010011101101010 #
b0000110000110100 $
0%
1'
0)
b0010011101101010 *
b0000110000110100 +
b1111001110101111 -
b0000110000110100 .
11
b0010011101101010 4
b1111001110101111 6
b1111001110101111 7
b11111111111111001110101111011111101100001001010110011101 8
b000000100001100010111011011101100101100001001000 9
1:
b1111001110101111 =
b0000110000110100 ?
b0000110000110100 @
#200000000
0!
0'
01
0:
#205000000
1!
b0010011011101001 #
b0000110001010001 $
0%
1'
0)
b0010011011101001 *
b0000110001010001 +
b1111001111011001 -
b0000110001010001 .
11
b0010011011101001 4
b1111001111011001 6
b1111001111011001 7
b11111111111111001111011001110100000010101000111010010100 8
b000000100001110110110110111110010111110111111010 9
1:
b1111001111011001 =
b0000110001010001 ?
b0000110001010001 @
#210000000
0!
0'
01
0:
#215000000
1!
b0010011010001001 #
b0000110000100111 $
0%
1'
0)
b0010011010001001 *
b0000110000100111 +
b1111010000111101 -
b0000110000100111 .
11
b0010011010001001 4
b1111010000111101 6
b1111010000111101 7
b11111111111111010000111101010010111000011010001001111000 8
b000000100001011001111111101011100101000000110110 9
1:
b1111010000111101 =
b0000110000100111 ?
b0000110000100111 @
#220000000
0!
0'
01
0:
#225000000
1!
b0010011000101001 #
b0000101111000011 $
0%
1'
0)
b0010011000101001 *
b0000101111000011 +
b1111010011000110 -
b0000101111000011 .
11
b0010011000101001 4
b1111010011000110 6
b1111010011000110 7
b11111111111111010011000110001100011100011010110110000011 8
b000000100000010101010001010111001101011100001110 9
1:
b1111010011000110 =
b0000101111000011 ?
b0000101111000011 @
#230000000
0!
0'
01
0:
#235000000
1!
b0010010111101001 #
b0000101100111010 $
0%
1'
0)
b0010010111101001 *
b0000101100111010 +
b1111010101110111 -
b0000101100111010 .
11
b0010010111101001 4
b1111010101110111 6
b1111010101110111 7
b11111111111111010101110111110110100010111011000010101110 8
b000000011110110111000111101010101010100101100100 9
1:
b1111010101110111 =
b0000101100111010 ?
b0000101100111010 @
#240000000
0!
0'
01
0:
#245000000
1!
b0010010111001001 #
b0000101010001001 $
0%
1'
0)
b0010010111001001 *
b0000101010001001 +
b1111011001010001 -
b0000101010001001 .
11
b0010010111001001 4
b1111011001010001 6
b1111011001010001 7
b11111111111111011001010001010011110100111011111101110110 8
b000000011100111101011110101001001011000110101010 9
1:
b1111011001010001 =
b0000101010001001 ?
b0000101010001001 @
#250000000
0!
0'
01
0:
#255000000
1!
b0010010110001001 #
b0000100110101111 $
0%
1'
0)
b0010010110001001 *
b0000100110101111 +
b1111011100100111 -
b0000100110101111 .
11
b0010010110001001 4
b1111011100100111 6
b1111011100100111 7
b11111111111111011100100111100001101011010100000000100101 8
b000000011010100111101010010011110011111000000110 9
1:
b1111011100100111 =
b0000100110101111 ?
b0000100110101111 @
#260000000
0!
0'
01
0:
#265000000
1!
b0010010101001001 #
b0000100011011001 $
0%
1'
0)
b0010010101001001 *
b0000100011011001 +
b1111011111100010 -
b0000100011011001 .
11
b0010010101001001 4
b1111011111100010 6
b1111011111100010 7
b11111111111111011111100010100001101011011111100100010001 8
b000000011000010100100101111010001001000111001010 9
1:
b1111011111100010 =
b0000100011011001 ?
b0000100011011001 @
#270000000
0!
0'
01
0:
#275000000
1!
b0010010100001001 #
b0000100000011110 $
0%
1'
0)
b0010010100001001 *
b0000100000011110 +
b1111100010101001 -
b0000100000011110 .
11
b0010010100001001 4
b1111100010101001 6
b1111100010101001 7
b11111111111111100010101001110010011011110001100100011110 8
b000000010110010100000101000011011010011110001100 9
1:
b1111100010101001 =
b0000100000011110 ?
b0000100000011110 @
#280000000
0!
0'
01
0:
#285000000
1!
b0010010010001001 #
b0000011101010111 $
0%
1'
0)
b0010010010001001 *
b0000011101010111 +
b1111100101000011 -
b0000011101010111 .
11
b0010010010001001 4
b1111100101000011 6
b1111100101000011 7
b11111111111111100101000011001010100100010010010011011000 8
b000000010100001011010100011001100110011100010110 9
1:
b1111100101000011 =
b0000011101010111 ?
b0000011101010111 @
#290000000
0!
0'
01
0:
#295000000
1!
b0010010000101001 #
b0000011010111101 $
0%
1'
0)
b0010010000101001 *
b0000011010111101 +
b1111100111001110 -
b0000011010111101 .
11
b0010010000101001 4
b1111100111001110 6
b1111100111001110 7
b11111111111111100111001110000001100101001011111101010111 8
b000000010010100001011110111111010110100111110010 9
1:
b1111100111001110 =
b0000011010111101 ?
b0000011010111101 @
#300000000
0!
0'
01
0:
#305000000
1!
b0010001111001001 #
b0000011000110010 $
0%
1'
0)
b0010001111001001 *
b0000011000110010 +
b1111101001111011 -
b0000011000110010 .
11
b0010001111001001 4
b1111101001111011 6
b1111101001111011 7
b11111111111111101001111011100000111111110000001101110001 8
b000000010001000001111101010100111101100010010100 9
1:
b1111101001111011 =
b0000011000110010 ?
b0000011000110010 @
#310000000
0!
0'
01
0:
#315000000
1!
b0010001110001001 #
b0000010110000101 $
0%
1'
0)
b0010001110001001 *
b0000010110000101 +
b1111101100100110 -
b0000010110000101 .
11
b0010001110001001 4
b1111101100100110 6
b1111101100100110 7
b11111111111111101100100110000010110010111010110001101000 8
b000000001111001011000100001111001010100001000010 9
1:
b1111101100100110 =
b0000010110000101 ?
b0000010110000101 @
#320000000
0!
0'
01
0:
#325000000
1!
b0010001101001001 #
b0000010011011010 $
0%
1'
0)
b0010001101001001 *
b0000010011011010 +
b1111101111011000 -
b0000010011011010 .
11
b0010001101001001 4
b1111101111011000 6
b1111101111011000 7
b11111111111111101111011000001100001001010010001101010101 8
b000000001101010101100011000111001101101110100100 9
1:
b1111101111011000 =
b0000010011011010 ?
b0000010011011010 @
#330000000
0!
0'
01
0:
#335000000
1!
b0010001100001000 #
b0000010000101000 $
0%
1'
0)
b0010001100001000 *
b0000010000101000 +
b1111110001111000 -
b0000010000101000 .
11
b0010001100001000 4
b1111110001111000 6
b1111110001111000 7
b11111111111111110001111000111010001101000000111110100111 8
b000000001011011011001110000110110011001000010000 9
1:
b1111110001111000 =
b0000010000101000 ?
b0000010000101000 @
#340000000
0!
0'
01
0:
#345000000
1!
b0010001011001000 #
b0000001110001000 $
0%
1'
0)
b0010001011001000 *
b0000001110001000 +
b1111110100001000 -
b0000001110001000 .
11
b0010001011001000 4
b1111110100001000 6
b1111110100001000 7
b11111111111111110100001000000111101001111101101101100001 8
b000000001001101101010000110011000000100111010000 9
1:
b1111110100001000 =
b0000001110001000 ?
b0000001110001000 @
#350000000
0!
0'
01
0:
#355000000
1!
b0010001010101000 #
b0000001011111000 $
0%
1'
0)
b0010001010101000 *
b0000001011111000 +
b1111110110100011 -
b0000001011111000 .
11
b0010001010101000 4
b1111110110100011 6
b1111110110100011 7
b11111111111111110110100011011100001001100010110111100110 8
b000000001000001010010011001101111111111100110000 9
1:
b1111110110100011 =
b0000001011111000 ?
b0000001011111000 @
#360000000
0!
0'
01
0:
#365000000
1!
b0010001010001000 #
b0000001001011101 $
0%
1'
0)
b0010001010001000 *
b0000001001011101 +
b1111111000111001 -
b0000001001011101 .
11
b0010001010001000 4
b1111111000111001 6
b1111111000111001 7
b11111111111111111000111001001010011011111101100010100110 8
b000000000110011111110001110100110101000000110010 9
1:
b1111111000111001 =
b0000001001011101 ?
b0000001001011101 @
#370000000
0!
0'
01
0:
#375000000
1!
b0000000111000111 $
0%
1'
0)
b0000000111000111 +
b1111111011001010 -
b0000000111000111 .
11
b1111111011001010 6
b1111111011001010 7
b11111111111111111011001010100010111111000100101110101010 8
b000000000100111000101100010110010001101001110110 9
1:
b1111111011001010 =
b0000000111000111 ?
b0000000111000111 @
#380000000
0!
0'
01
0:
#385000000
1!
b0010001001101000 #
b0000000100110110 $
0%
1'
0)
b0010001001101000 *
b0000000100110110 +
b1111111101000101 -
b0000000100110110 .
11
b0010001001101000 4
b1111111101000101 6
b1111111101000101 7
b11111111111111111101000101110010011110100001100100011001 8
b000000000011010101000010110010010101110111111100 9
1:
b1111111101000101 =
b0000000100110110 ?
b0000000100110110 @
#390000000
0!
0'
01
0:
#395000000
1!
b0010001001001000 #
b0000000010111011 $
0%
1'
0)
b0010001001001000 *
b0000000010111011 +
b1111111110011000 -
b0000000010111011 .
11
b0010001001001000 4
b1111111110011000 6
b1111111110011000 7
b11111111111111111110011000010101010001010000000001010100 8
b000000000010000000100000110110101110101000111110 9
1:
b1111111110011000 =
b0000000010111011 ?
b0000000010111011 @
#400000000
0!
0'
01
0:
#405000000
1!
b0010001000101000 #
b0000000001101000 $
0%
1'
0)
b0010001000101000 *
b0000000001101000 +
b1111111111100101 -
b0000000001101000 .
11
b0010001000101000 4
b1111111111100101 6
b1111111111100101 7
b11111111111111111111100101011100010000111111101101000111 8
b000000000001000111011110010000000100000010010000 9
1:
b1111111111100101 =
b0000000001101000 ?
b0000000001101000 @
#410000000
0!
0'
01
0:
#415000000
1!
b0010001000001000 #
b0000000000011011 $
0%
1'
0)
b0010001000001000 *
b0000000000011011 +
b0000000000100110 -
b0000000000011011 .
11
b0010001000001000 4
b0000000000100110 6
b0000000000100110 7
b00000000000000000000100110011100111010110001100001110111 8
b000000000000010010100011100010111100000111111110 9
1:
b0000000000100110 =
b0000000000011011 ?
b0000000000011011 @
#420000000
0!
0'
01
0:
#425000000
1!
b0010000111001000 #
b0000000000100110 $
0%
1'
0)
b0010000111001000 *
b0000000000100110 +
b0000000001000100 -
b0000000000100110 .
11
b0010000111001000 4
b0000000001000100 6
b0000000001000100 7
b00000000000000000001000100011100010000101010010101010001 8
b111111111111100101111000101000111001100110100100 9
1:
b0000000001000100 =
b0000000000100110 ?
b0000000000100110 @
#430000000
0!
0'
01
0:
#435000000
1!
b0010000110101000 #
b0000000001000100 $
0%
1'
0)
b0010000110101000 *
b0000000001000100 +
b0000000001100010 -
b0000000001000100 .
11
b0010000110101000 4
b0000000001100010 6
b0000000001100010 7
b00000000000000000001100010010011000101110011110001111011 8
b111111111111010001010001001001001100001000011000 9
1:
b0000000001100010 =
b0000000001000100 ?
b0000000001000100 @
#440000000
0!
0'
01
0:
#445000000
1!
b0010000101101000 #
b0000000001100010 $
0%
1'
0)
b0010000101101000 *
b0000000001100010 +
b0000000001111010 -
b0000000001100010 .
11
b0010000101101000 4
b0000000001111010 6
b0000000001111010 7
b00000000000000000001111010101011001000010110110010001011 8
b111111111110111100101001101001011110101010001100 9
1:
b0000000001111010 =
b0000000001100010 ?
b0000000001100010 @
#450000000
0!
0'
01
0:
#455000000
1!
b0000000001111010 $
0%
1'
0)
b0000000001111010 +
b0000000010011001 -
b0000000001111010 .
11
b0000000010011001 6
b0000000010011001 7
b00000000000000000010011001110111110100100101110100010110 8
b111111111110101100001010000011010011111000011100 9
1:
b0000000010011001 =
b0000000001111010 ?
b0000000001111010 @
#460000000
0!
0'
01
0:
#465000000
1!
b0010000101001000 #
b0000000010011001 $
0%
1'
0)
b0010000101001000 *
b0000000010011001 +
b0000000011000101 -
b0000000010011001 .
11
b0010000101001000 4
b0000000011000101 6
b0000000011000101 7
b00000000000000000011000101001010010101001001101010001100 8
b111111111110010110110110100100101011010010110110 9
1:
b0000000011000101 =
b0000000010011001 ?
b0000000010011001 @
#470000000
0!
0'
01
0:
#475000000
1!
b0000000011000101 $
0%
1'
0)
b0000000011000101 +
b0000000011011010 -
b0000000011000101 .
11
b0000000011011010 6
b0000000011011010 7
b00000000000000000011011010111101011011100110111010101010 8
b111111111101111000100111010100000010001100111110 9
1:
b0000000011011010 =
b0000000011000101 ?
b0000000011000101 @
#480000000
0!
0'
01
0:
#485000000
1!
b0010000101101000 #
b0000000011011010 $
0%
1'
0)
b0010000101101000 *
b0000000011011010 +
b0000000100010001 -
b0000000011011010 .
11
b0010000101101000 4
b0000000100010001 6
b0000000100010001 7
b00000000000000000100010001100100011010011001011111100101 8
b111111111101101010001011101010101000110001011100 9
1:
b0000000100010001 =
b0000000011011010 ?
b0000000011011010 @
#490000000
0!
0'
01
0:
#495000000
1!
b0010000110001000 #
b0000000100010001 $
0%
1'
0)
b0010000110001000 *
b0000000100010001 +
b0000000101000111 -
b0000000100010001 .
11
b0010000110001000 4
b0000000101000111 6
b0000000101000111 7
b00000000000000000101000111110101000010110111101100000110 8
b111111111101000100011000100101110101011010000110 9
1:
b0000000101000111 =
b0000000100010001 ?
b0000000100010001 @
#500000000
0!
0'
01
0:
